hyperliquid_monitor/__init__.py
hyperliquid_monitor/config.py
hyperliquid_monitor/database.py
hyperliquid_monitor/monitor.py
hyperliquid_monitor/types.py
hyperliquid_monitor-0.1.2.1.dist-info/LICENSE.md
hyperliquid_monitor-0.1.2.1.dist-info/METADATA
hyperliquid_monitor-0.1.2.1.dist-info/WHEEL
hyperliquid_monitor-0.1.2.1.dist-info/RECORD
