Metadata-Version: 2.1
Name: hyperliquid-monitor
Version: 0.1.2.1
Summary: A Hyperliquid trade monitor package
Home-page: https://github.com/oni-giri/hyperliquid-monitor
License: MIT
Keywords: hyperliquid,trading,cryptocurrency,monitor,dex
Author: Yakitori
Requires-Python: >=3.9,<4.0
Classifier: Development Status :: 4 - Beta
Classifier: Intended Audience :: Developers
Classifier: License :: OSI Approved :: MIT License
Classifier: Programming Language :: Python :: 3
Classifier: Programming Language :: Python :: 3.9
Classifier: Programming Language :: Python :: 3.10
Classifier: Programming Language :: Python :: 3.11
Classifier: Programming Language :: Python :: 3.12
Classifier: Programming Language :: Python :: 3.13
Classifier: Topic :: Office/Business :: Financial :: Investment
Classifier: Topic :: Software Development :: Libraries :: Python Modules
Requires-Dist: hyperliquid-python-sdk (>=0.8.0,<0.9.0)
Requires-Dist: python-dotenv (>=1.0.0,<2.0.0)
Project-URL: Repository, https://github.com/oni-giri/hyperliquid-monitor
